estacionalidad/Plot/__init__.py
estacionalidad/Plot/abstract_clases.py
estacionalidad/Plot/config.py
estacionalidad/Plot/table.py
estacionalidad/Wrangling/__init__.py
estacionalidad/Wrangling/read_series_indices_indec.py
estacionalidad/__init__.py
estacionalidad/fonts/Helvetica-Neue-LT-Std-77-Bold-Condensed_22542.ttf
estacionalidad-0.1.9.dist-info/METADATA
estacionalidad-0.1.9.dist-info/WHEEL
estacionalidad-0.1.9.dist-info/RECORD
